{"Withheld":false,"Lines":[{"Position":"1","ShowPosition":true,"RacingNumber":"44","Tla":"HAM","BroadcastName":"L HAMILTON","FullName":"Lewis HAMILTON","Team":"Mercedes","TeamColour":"00D2BE","LapTime":"1:23.691","LapState":83,"DiffToAhead":"","DiffToLeader":"","OverallFastest":true,"PersonalFastest":true},{"Position":"2","ShowPosition":true,"RacingNumber":"31","Tla":"OCO","BroadcastName":"E OCON","FullName":"Esteban OCON","Team":"Alpine","TeamColour":"0090FF","LapTime":"1:24.034","LapState":81,"DiffToAhead":"+0.343","DiffToLeader":"+0.343","OverallFastest":false,"PersonalFastest":true},{"Position":"3","ShowPosition":true,"RacingNumber":"77","Tla":"BOT","BroadcastName":"V BOTTAS","FullName":"Valtteri BOTTAS","Team":"Mercedes","TeamColour":"00D2BE","LapTime":"1:24.083","LapState":81,"DiffToAhead":"+0.049","DiffToLeader":"+0.392","OverallFastest":false,"PersonalFastest":true}]}