{"Withheld":false,"Lines":[{"Position":"1","ShowPosition":true,"RacingNumber":"44","Tla":"HAM","BroadcastName":"L HAMILTON","FullName":"Lewis HAMILTON","Team":"Mercedes","TeamColour":"00d2be","LapTime":"1:08.320","LapState":83,"DiffToAhead":"","DiffToLeader":"","OverallFastest":true,"PersonalFastest":true},{"Position":"2","ShowPosition":true,"RacingNumber":"33","Tla":"VER","BroadcastName":"M VERSTAPPEN","FullName":"Max VERSTAPPEN","Team":"Red Bull Racing","TeamColour":"1e41ff","LapTime":"1:08.346","LapState":81,"DiffToAhead":"+0.026","DiffToLeader":"+0.026","OverallFastest":false,"PersonalFastest":true},{"Position":"3","ShowPosition":true,"RacingNumber":"16","Tla":"LEC","BroadcastName":"C LECLERC","FullName":"Charles LECLERC","Team":"Ferrari","TeamColour":"dc0000","LapTime":"1:08.611","LapState":81,"DiffToAhead":"+0.265","DiffToLeader":"+0.291","OverallFastest":false,"PersonalFastest":true}]}