{"Withheld":false,"Lines":[{"Position":"1","ShowPosition":true,"RacingNumber":"5","Tla":"VET","BroadcastName":"S VETTEL","FullName":"Sebastian VETTEL","Team":"Ferrari","TeamColour":"DC0000","LapTime":"1:21.105","LapState":83,"DiffToAhead":"","DiffToLeader":"","OverallFastest":true,"PersonalFastest":true},{"Position":"2","ShowPosition":true,"RacingNumber":"7","Tla":"RAI","BroadcastName":"K RAIKKONEN","FullName":"Kimi RAIKKONEN","Team":"Ferrari","TeamColour":"DC0000","LapTime":"1:21.375","LapState":81,"DiffToAhead":"+0.270","DiffToLeader":"+0.270","OverallFastest":false,"PersonalFastest":true},{"Position":"3","ShowPosition":true,"RacingNumber":"44","Tla":"HAM","BroadcastName":"L HAMILTON","FullName":"Lewis HAMILTON","Team":"Mercedes","TeamColour":"00D2BE","LapTime":"1:21.392","LapState":81,"DiffToAhead":"+0.017","DiffToLeader":"+0.287","OverallFastest":false,"PersonalFastest":true}]}